section_detection/__init__.py
section_detection/section.py
section_detection/section_rule.py
section_detection/sectionizer.py
section_detection/util.py
kr_medspacy-0.0.9.dist-info/METADATA
kr_medspacy-0.0.9.dist-info/WHEEL
kr_medspacy-0.0.9.dist-info/top_level.txt
kr_medspacy-0.0.9.dist-info/RECORD
