Metadata-Version: 2.1
Name: kr-medspacy
Version: 0.0.9
Summary: Korean version of medspacy
Author: SungJoo Byun
Author-email: byunsj@snu.ac.kr
License: MIT
Keywords: clinical NLP,clinical NER,medspacy,Korean clinical NLP,medical NLP
